MANIFEST.in
README.rst
setup.py
version.txt
micral_name_core/CrystNet2.1.hdf5
micral_name_core/__init__.py
micral_name_core/micral_name_core.py
micral_name_core/version.txt
micral_name_core.egg-info/PKG-INFO
micral_name_core.egg-info/SOURCES.txt
micral_name_core.egg-info/dependency_links.txt
micral_name_core.egg-info/not-zip-safe
micral_name_core.egg-info/requires.txt
micral_name_core.egg-info/top_level.txt