Metadata-Version: 1.0
Name: micral-name-core
Version: 2.0
Summary: Name tool between 7 available
Home-page: UNKNOWN
Author: Yann LEROY
Author-email: yann.leroy102@orange.fr
License: MIT
Platform: UNKNOWN
